agentsys/__init__.py
agentsys/types.py
agentsys/util.py
agentsys-0.7.0.dist-info/LICENSE
agentsys-0.7.0.dist-info/METADATA
agentsys-0.7.0.dist-info/WHEEL
agentsys-0.7.0.dist-info/top_level.txt
agentsys-0.7.0.dist-info/RECORD
