Metadata-Version: 2.1
Name: agentsys
Version: 0.7.0
Summary: An educational multi-agent orchestration framework
Author: lifsys
License: MIT License
Project-URL: Homepage, https://github.com/lifsys/agentsys
Project-URL: Issues, https://github.com/lifsys/agentsys/issues
Keywords: ai,agents,orchestration,multi-agent
Classifier: Development Status :: 3 - Alpha
Classifier: Intended Audience :: Developers
Classifier: License :: OSI Approved :: MIT License
Classifier: Programming Language :: Python :: 3
Classifier: Programming Language :: Python :: 3.10
Requires-Python: >=3.10
License-File: LICENSE
Requires-Dist: openai >=1.0.0
Requires-Dist: pydantic >=2.0.0
Requires-Dist: locksys >=0.1.0
Provides-Extra: dev
Requires-Dist: pytest ; extra == 'dev'
Requires-Dist: pytest-cov ; extra == 'dev'
Requires-Dist: pytest-mock ; extra == 'dev'
Requires-Dist: pytest-asyncio ; extra == 'dev'
Requires-Dist: black ; extra == 'dev'
